chuchichaestli/__about__.py
chuchichaestli/__init__.py
chuchichaestli/utils.py
chuchichaestli/data/__init__.py
chuchichaestli/data/cache.py
chuchichaestli/data/dataset.py
chuchichaestli/debug/__init__.py
chuchichaestli/debug/memory_usage.py
chuchichaestli/debug/visitor.py
chuchichaestli/diffusion/__init__.py
chuchichaestli/diffusion/distributions.py
chuchichaestli/diffusion/ddpm/__init__.py
chuchichaestli/diffusion/ddpm/base.py
chuchichaestli/diffusion/ddpm/bbdm.py
chuchichaestli/diffusion/ddpm/cfg_ddpm.py
chuchichaestli/diffusion/ddpm/ddim.py
chuchichaestli/diffusion/ddpm/ddpm.py
chuchichaestli/diffusion/ddpm/indi.py
chuchichaestli/diffusion/ddpm/prior_grad.py
chuchichaestli/diffusion/ddpm/shift_ddpm.py
chuchichaestli/metrics/__init__.py
chuchichaestli/metrics/base.py
chuchichaestli/metrics/fid.py
chuchichaestli/metrics/functional.py
chuchichaestli/metrics/lpips.py
chuchichaestli/metrics/mse.py
chuchichaestli/metrics/psnr.py
chuchichaestli/metrics/ssim.py
chuchichaestli/models/__init__.py
chuchichaestli/models/activations.py
chuchichaestli/models/blocks.py
chuchichaestli/models/downsampling.py
chuchichaestli/models/maps.py
chuchichaestli/models/norm.py
chuchichaestli/models/resnet.py
chuchichaestli/models/upsampling.py
chuchichaestli/models/adversarial/__init__.py
chuchichaestli/models/adversarial/discriminator.py
chuchichaestli/models/attention/__init__.py
chuchichaestli/models/attention/attention_gate.py
chuchichaestli/models/attention/conv_attention.py
chuchichaestli/models/attention/multiscale_attention.py
chuchichaestli/models/attention/self_attention.py
chuchichaestli/models/autoencoder/__init__.py
chuchichaestli/models/autoencoder/autoencoder.py
chuchichaestli/models/autoencoder/dcae.py
chuchichaestli/models/autoencoder/decoder.py
chuchichaestli/models/autoencoder/encoder.py
chuchichaestli/models/autoencoder/vae.py
chuchichaestli/models/autoencoder/vqvae.py
chuchichaestli/models/unet/__init__.py
chuchichaestli/models/unet/time_embeddings.py
chuchichaestli-0.2.17.dist-info/METADATA
chuchichaestli-0.2.17.dist-info/WHEEL
chuchichaestli-0.2.17.dist-info/licenses/LICENSE
chuchichaestli-0.2.17.dist-info/RECORD
