Metadata-Version: 2.4
Name: chuchichaestli
Version: 0.2.17
Summary: Where you find all the state-of-the-art cooking utensils (salt, pepper, gradient descent... the usual).
Project-URL: Documentation, https://github.com/CAIIVS/chuchichaestli#readme
Project-URL: Homepage, https://github.com/CAIIVS/chuchichaestli
Project-URL: Repository, https://github.com/CAIIVS/chuchichaestli.git
Project-URL: Issues, https://github.com/CAIIVS/chuchichaestli/issues
Project-URL: Source, https://github.com/CAIIVS/chuchichaestli
Author-email: Yann Billeter <bily@zhaw.ch>, Daniel Barco <baoc@zhaw.ch>, Philipp Denzel <denp@zhaw.ch>, Martin Oswald <oswd@zhaw.ch>, Marc Stadelmann <stmd@zhaw.ch>
Maintainer-email: Daniel Barco <baoc@zhaw.ch>, Philipp Denzel <denp@zhaw.ch>, Marc Stadelmann <stmd@zhaw.ch>
License-Expression: GPL-3.0-or-later
License-File: LICENSE
Keywords: artificial intelligence,deep learning,neural networks
Classifier: License :: OSI Approved :: GNU General Public License v3 or later (GPLv3+)
Classifier: Operating System :: OS Independent
Classifier: Programming Language :: Python :: 3
Classifier: Programming Language :: Python :: 3.10
Classifier: Programming Language :: Python :: 3.11
Classifier: Programming Language :: Python :: 3.12
Classifier: Programming Language :: Python :: 3.13
Classifier: Topic :: Scientific/Engineering :: Artificial Intelligence
Classifier: Topic :: Scientific/Engineering :: Image Processing
Requires-Python: >=3.10
Requires-Dist: h5py>=3.12.1
Requires-Dist: numpy>=1.26
Requires-Dist: torch>=2.2.2
Requires-Dist: torchvision>=0.20.1
Provides-Extra: dev
Requires-Dist: pytest-cov>=6.2.1; extra == 'dev'
Requires-Dist: pytest==8.1.1; extra == 'dev'
Requires-Dist: ruff==0.4.1; extra == 'dev'
Provides-Extra: docs
Requires-Dist: mkdocs-api-autonav>=0.3.0; extra == 'docs'
Requires-Dist: mkdocs-material>=9.6.16; extra == 'docs'
Requires-Dist: mkdocs>=1.6.1; extra == 'docs'
Requires-Dist: mkdocstrings[python]>=0.30.0; extra == 'docs'
